command_service/__init__.py
command_service/main.py
mycmd-0.0.2.dist-info/LICENSE
mycmd-0.0.2.dist-info/METADATA
mycmd-0.0.2.dist-info/WHEEL
mycmd-0.0.2.dist-info/entry_points.txt
mycmd-0.0.2.dist-info/top_level.txt
mycmd-0.0.2.dist-info/RECORD
