Metadata-Version: 2.1
Name: mycmd
Version: 0.0.2
Summary: CLI for My Command Service.
Home-page: https://github.com/cyberlabrs/my-commands-cli
Author: Andrija Vojnovic
Author-email: andrija.vojnovic@cyberlab.rs
License: MIT
Keywords: cyberlab my command  python package
Platform: UNKNOWN
Classifier: Programming Language :: Python :: 3
Classifier: License :: OSI Approved :: MIT License
Classifier: Operating System :: OS Independent
License-File: LICENSE
Requires-Dist: fire
Requires-Dist: six
Requires-Dist: setuptools
Requires-Dist: wheel
Requires-Dist: requests
